LICENSE
MANIFEST.in
README.rst
setup.py
changes/__init__.py
changes/changes.py
changes/models.py
changes/signals.py
changes/tests/__init__.py
changes/tests/models.py
changes/tests/run_tests.py
changes/tests/test_settings.py
changes/tests/tests.py
django_changes.egg-info/PKG-INFO
django_changes.egg-info/SOURCES.txt
django_changes.egg-info/dependency_links.txt
django_changes.egg-info/requires.txt
django_changes.egg-info/top_level.txt