Metadata-Version: 1.1
Name: django-changes
Version: 0.2.2
Summary: 
